metran/__init__.py
metran/factoranalysis.py
metran/kalmanfilter.py
metran/metran.py
metran/plots.py
metran/solver.py
metran/utils.py
metran/version.py
metran-0.4.0.dist-info/LICENSE
metran-0.4.0.dist-info/METADATA
metran-0.4.0.dist-info/WHEEL
metran-0.4.0.dist-info/top_level.txt
metran-0.4.0.dist-info/RECORD
