Metadata-Version: 2.1
Name: metran
Version: 0.4.0
Summary: Python package to perform timeseries analysis of multiple hydrological time series using a dynamic factor model.
Author: W.L. Berendrecht
Maintainer-email: "W.L. Berendrecht" <wilbert@berendrechtconsultancy.nl>, "D.A. Brakenhoff" <d.brakenhoff@artesia-water.nl>, "M.A. Vonk" <m.vonk@artesia-water.nl>
License: The MIT License (MIT)
Project-URL: homepage, https://github.com/pastas/metran
Project-URL: repository, https://github.com/pastas/metran
Project-URL: documentation, https://metran.readthedocs.io/en/latest/
Keywords: hydrology,groundwater,timeseries,analysis
Classifier: Development Status :: 4 - Beta
Classifier: Intended Audience :: Science/Research
Classifier: Intended Audience :: Other Audience
Classifier: License :: OSI Approved :: MIT License
Classifier: Programming Language :: Python :: 3 :: Only
Classifier: Programming Language :: Python :: 3.8
Classifier: Programming Language :: Python :: 3.9
Classifier: Programming Language :: Python :: 3.10
Classifier: Programming Language :: Python :: 3.11
Classifier: Programming Language :: Python :: 3.12
Classifier: Topic :: Scientific/Engineering :: Hydrology
Requires-Python: >=3.8
License-File: LICENSE
Requires-Dist: numpy >=1.16.5
Requires-Dist: matplotlib >=3.0
Requires-Dist: pandas >=1.0
Requires-Dist: scipy >=1.1
Requires-Dist: numba
Requires-Dist: pastas >=0.16.0
Provides-Extra: coveraging
Requires-Dist: coverage ; extra == 'coveraging'
Provides-Extra: dev
Requires-Dist: metran[coveraging,linting,pytesting,solvers] ; extra == 'dev'
Requires-Dist: tox ; extra == 'dev'
Provides-Extra: dino
Requires-Dist: hydropandas ; extra == 'dino'
Provides-Extra: formatting
Requires-Dist: black[jupyter] ; extra == 'formatting'
Requires-Dist: isort ; extra == 'formatting'
Provides-Extra: full
Requires-Dist: metran[solvers] ; extra == 'full'
Provides-Extra: linting
Requires-Dist: flake8 ; extra == 'linting'
Provides-Extra: pytesting
Requires-Dist: pytest ; extra == 'pytesting'
Requires-Dist: pytest-cov ; extra == 'pytesting'
Requires-Dist: pytest-sugar ; extra == 'pytesting'
Requires-Dist: jupyter ; extra == 'pytesting'
Provides-Extra: rtd
Requires-Dist: metran[dino] ; extra == 'rtd'
Requires-Dist: sphinx-rtd-theme ; extra == 'rtd'
Requires-Dist: Ipython ; extra == 'rtd'
Requires-Dist: ipykernel ; extra == 'rtd'
Requires-Dist: nbsphinx ; extra == 'rtd'
Requires-Dist: nbsphinx-link ; extra == 'rtd'
Requires-Dist: jupyter ; extra == 'rtd'
Provides-Extra: solvers
Requires-Dist: lmfit >=1.0.0 ; extra == 'solvers'
